Metadata-Version: 2.4
Name: mcko2025sol
Version: 0.1
Summary: solutions for some tasks
Author-email: genialnaydver@gmail.com
Dynamic: author-email
Dynamic: summary
